odoo/addons/base_action_visibility_restriction_domain/README.rst
odoo/addons/base_action_visibility_restriction_domain/__init__.py
odoo/addons/base_action_visibility_restriction_domain/__manifest__.py
odoo/addons/base_action_visibility_restriction_domain/hooks.py
odoo/addons/base_action_visibility_restriction_domain/i18n/base_action_visibility_restriction_domain.pot
odoo/addons/base_action_visibility_restriction_domain/i18n/it.po
odoo/addons/base_action_visibility_restriction_domain/models/__init__.py
odoo/addons/base_action_visibility_restriction_domain/models/ir_actions.py
odoo/addons/base_action_visibility_restriction_domain/readme/CONTRIBUTORS.rst
odoo/addons/base_action_visibility_restriction_domain/readme/DESCRIPTION.rst
odoo/addons/base_action_visibility_restriction_domain/readme/USAGE.rst
odoo/addons/base_action_visibility_restriction_domain/security/ir.model.access.csv
odoo/addons/base_action_visibility_restriction_domain/static/description/icon.png
odoo/addons/base_action_visibility_restriction_domain/tests/__init__.py
odoo/addons/base_action_visibility_restriction_domain/tests/test_base_action_visibility_restriction_domain.py
odoo/addons/base_action_visibility_restriction_domain/views/ir_actions_views.xml
odoo14_addon_base_action_visibility_restriction_domain-14.0.1.0.1.dev4.dist-info/METADATA
odoo14_addon_base_action_visibility_restriction_domain-14.0.1.0.1.dev4.dist-info/WHEEL
odoo14_addon_base_action_visibility_restriction_domain-14.0.1.0.1.dev4.dist-info/top_level.txt
odoo14_addon_base_action_visibility_restriction_domain-14.0.1.0.1.dev4.dist-info/RECORD
